{
    "all": {
        "include": {
            "all": [
                "adw-gtk3-theme",
                "alsa-firmware",
                "android-udev-rules",
                "apr-util",
                "apr",
                "bootc",
                "conky",
                "distrobox",
                "ffmpeg-libs",
                "ffmpeg",
                "ffmpegthumbnailer",
                "fzf",
                "gnome-tweaks",
                "grub2-tools-extra",
                "heif-pixbuf-loader",
                "htop",
                "intel-media-driver",
                "iotop",
                "kernel-tools",
                "libheif-freeworld",
                "libheif-tools",
                "libratbag-ratbagd",
                "libva-intel-driver",
                "libva-utils",
                "lshw",
                "mesa-va-drivers-freeworld",
                "net-tools",
                "nethogs",
                "nvme-cli",
                "nvtop",
                "openrgb-udev-rules",
                "openssh-server",
                "openssl",
                "oversteer-udev",
                "pam_yubico",
                "pam-u2f",
                "pamu2fcfg",
                "pipewire-codec-aptx",
                "podman-compose",
                "powertop",
                "smartmontools",
                "solaar-udev",
                "sshpass",
                "symlinks",
                "tcpdump",
                "tmux",
                "traceroute",
                "vim",
                "vim",
                "wireguard-tools",
                "zstd"
            ]
        },
        "exclude": {
            "all": [
                "default-fonts-cjk-sans",
                "firefox-langpacks",
                "firefox",
                "google-noto-sans-cjk-vf-fonts",
                "libavcodec-free",
                "libavdevice-free",
                "libavfilter-free",
                "libavformat-free",
                "libavutil-free",
                "libpostproc-free",
                "libswresample-free",
                "libswscale-free",
                "mesa-va-drivers"
            ]
        }
    }
}
